[{"accountBfoId":"001A000000f77EIIAY","id":318735,"active":null,"country":"India","companyName":"Industrial Associates","address1":"Plot No. 26, Commercial Complex, Light Industrial Area, Nandini Road, Bhilai`","address2":null,"zipCode":"490026","city":"Bhilai","phone":null,"email":null,"webSite":null,"webSite2":null,"createdBy":null,"createdOn":null,"updatedBy":null,"updatedOn":null,"b2cPhoto":null,"countryId":219,"latitude":21.216667,"longitude":81.433334,"administrativeRegion":"chhattisgarh","stateId":1237,"webshop":null,"emailExists":true,"phoneExists":true,"openingHoursType":"NOT_SET","partnerDetails":{"firstName":"Krishna","lastName":"heshwari","partnerContact":{"email":"giriraj2k14@gmail.com","phone":"0788-2261681"},"about":null,"logoBase64":null,"photoUrl":null,"addressTemplate1":null,"addressTemplate2":null,"detailsAddressTemplate1":null,"detailsAddressTemplate2":null,"detailsAddressTemplate3":null,"descriptions":[{"id":null,"languageId":null,"description":null,"isDefault":true}]},"openingHours":[],"preferredMarketServe":[],"competence":[],"areaOfFocus":[],"programLevels":[],"eshop":false,"federatedId":null}]