[{"accountBfoId":"0011H00001NG7b5QAD","id":353474,"active":null,"country":"New Zealand","companyName":"Telfer Electrical Cromwell Ltd","address1":"Unit1 2A Ree Crescent","address2":null,"zipCode":"9310","city":"Cromwell","phone":null,"email":null,"webSite":"http://www.telfers.co.nz/","webSite2":null,"createdBy":null,"createdOn":null,"updatedBy":null,"updatedOn":null,"b2cPhoto":null,"countryId":71,"latitude":-45.05061,"longitude":169.18907,"administrativeRegion":null,"stateId":null,"webshop":null,"emailExists":true,"phoneExists":true,"openingHoursType":"NOT_SET","partnerDetails":{"firstName":null,"lastName":null,"partnerContact":{"email":"sales@telferotago.co.nz","phone":"03 445 0892"},"about":null,"logoBase64":null,"photoUrl":null,"addressTemplate1":null,"addressTemplate2":null,"detailsAddressTemplate1":null,"detailsAddressTemplate2":null,"detailsAddressTemplate3":null,"descriptions":[{"id":null,"languageId":null,"description":null,"isDefault":true}]},"openingHours":[],"preferredMarketServe":[],"competence":[],"areaOfFocus":[],"programLevels":[],"eshop":null,"federatedId":null}]