[{"accountBfoId":"0011200001LKpfQAAT","id":386031,"active":null,"country":"New Zealand","companyName":"High Wire Electrical Limited","address1":"6/70 Bruce McLaren Road","address2":null,"zipCode":"0612","city":"Henderson","phone":null,"email":null,"webSite":"https://highwire.net.nz","webSite2":null,"createdBy":null,"createdOn":null,"updatedBy":null,"updatedOn":null,"b2cPhoto":null,"countryId":71,"latitude":-36.896214,"longitude":174.62721,"administrativeRegion":"Auckland","stateId":1462,"webshop":null,"emailExists":true,"phoneExists":true,"openingHoursType":"CALL","partnerDetails":{"firstName":"Alaric","lastName":"Jacobsen","partnerContact":{"email":"aj@highwire.net.nz","phone":"0508444494"},"about":"HighWire perform all electrical services at very competitive rates, with the highest quality workmanship, using the best products.\nWe have built an outstanding reputation on quality services, fantastic value, and fast response times.","logoBase64":null,"photoUrl":null,"addressTemplate1":null,"addressTemplate2":null,"detailsAddressTemplate1":null,"detailsAddressTemplate2":null,"detailsAddressTemplate3":null,"descriptions":[{"id":null,"languageId":null,"description":"HighWire perform all electrical services at very competitive rates, with the highest quality workmanship, using the best products.\nWe have built an outstanding reputation on quality services, fantastic value, and fast response times.","isDefault":true}]},"openingHours":[],"preferredMarketServe":[],"competence":[],"areaOfFocus":[],"programLevels":[{"id":null,"code":null,"label":null,"bfoId":null,"name":null,"position":null,"names":null,"selected":null,"createdBy":null,"createdOn":null,"updatedBy":null,"updatedOn":null,"usedBy":null,"bfoValidationState":null,"typeName":null,"ignored":null,"preferred":null,"logoUrl":"images/program-level_5948_1624949941404.jpg","displayRank":5,"global":null,"countryId":null,"countryLabel":null,"active":null,"programId":null,"program":null,"bfoLastData":null,"countryProgramLevels":null,"specializations":null,"globalProgramLevelId":null,"b2cAvailable":false}],"eshop":null,"federatedId":null}]