[{"accountBfoId":"001A000000kz4smIAA","id":344940,"active":null,"country":"Slovakia","companyName":"Elektro Haramia","address1":"Železničná 927","address2":null,"zipCode":"900 55","city":"Lozorno","phone":null,"email":null,"webSite":"www.elektroharamia.sk","webSite2":null,"createdBy":null,"createdOn":null,"updatedBy":null,"updatedOn":null,"b2cPhoto":null,"countryId":80,"latitude":48.337936,"longitude":17.042564,"administrativeRegion":null,"stateId":null,"webshop":null,"emailExists":true,"phoneExists":true,"openingHoursType":"NOT_SET","partnerDetails":{"firstName":null,"lastName":null,"partnerContact":{"email":"haramia@elektroharamia.sk","phone":"+421 2 65 96 82 67"},"about":null,"logoBase64":null,"photoUrl":null,"addressTemplate1":null,"addressTemplate2":null,"detailsAddressTemplate1":null,"detailsAddressTemplate2":null,"detailsAddressTemplate3":null,"descriptions":[{"id":null,"languageId":null,"description":null,"isDefault":true}]},"openingHours":[],"preferredMarketServe":[],"competence":[],"areaOfFocus":[],"programLevels":[],"eshop":null,"federatedId":null}]