{"id":386717,"companyName":"ТД ТЕК-УКРАЇНА ТОВ","address1":"вул. Незалежної України, буд. 41","address2":null,"zipCode":"69037","city":"Запоріжжя","administrativeRegion":null,"country":"Ukraine","countryId":19,"administrativeRegionId":null,"webSite":"http://tekua.com.ua/","webSite2":null,"emailExists":true,"phoneExists":true,"latitude":50.46935,"longitude":30.504885,"accountBfoId":"0011H00001OUSvLQAX","webShop":null,"active":true,"type":null,"isFromBfo":true,"eshop":false,"federatedId":"gb0066bd-57f0-9991-1d1a-768999322ec6","partnerDetails":{"firstName":"Ольга Жмурко","lastName":null,"partnerContact":{"email":"tekua@tekua.com.ua","phone":"38 (061) 213-46-99"},"about":null,"logoBase64":null,"photoUrl":null,"addressTemplate1":"${ct}","addressTemplate2":"","detailsAddressTemplate1":"${ad}${ca}","detailsAddressTemplate2":"${cp}${ct}${bfoSt}${con}","detailsAddressTemplate3":"","descriptions":[]},"areaOfFocus":[{"id":41,"code":"SI2","label":"Industrial Automation SI","bfoId":null,"name":"Industrial Automation SI","position":null,"names":null,"selected":null,"createdBy":null,"createdOn":null,"updatedBy":null,"updatedOn":null,"usedBy":null,"bfoValidationState":null,"typeName":null,"ignored":false,"preferred":null,"logoUrl":null}],"businessType":[{"id":10,"code":"SI","label":"System Integrator","bfoId":null,"name":"System Integrator","position":null,"names":null,"selected":null,"createdBy":null,"createdOn":null,"updatedBy":null,"updatedOn":null,"usedBy":null,"bfoValidationState":null,"typeName":null,"ignored":false,"preferred":null,"logoUrl":null}],"domainOfExpertise":[],"marketServe":[],"preferredMarketServe":[],"specialization":[{"id":2329,"code":"3900","label":"PLC, PAC and Dedicated Controllers","bfoId":null,"name":"PAC, PLC un citi kontrolleri","position":null,"names":null,"selected":null,"createdBy":null,"createdOn":null,"updatedBy":null,"updatedOn":null,"usedBy":null,"bfoValidationState":null,"typeName":null,"ignored":false,"preferred":null,"logoUrl":null},{"id":2315,"code":"2900","label":"Variable Speed Drives and Soft Starters","bfoId":null,"name":"Kustība un piedziņas","position":null,"names":null,"selected":null,"createdBy":null,"createdOn":null,"updatedBy":null,"updatedOn":null,"usedBy":null,"bfoValidationState":null,"typeName":null,"ignored":false,"preferred":null,"logoUrl":null},{"id":2331,"code":"2100","label":"Human Machine Interfaces (HMI)","bfoId":null,"name":"HMI (termināļi un industrialie PC)","position":null,"names":null,"selected":null,"createdBy":null,"createdOn":null,"updatedBy":null,"updatedOn":null,"usedBy":null,"bfoValidationState":null,"typeName":null,"ignored":false,"preferred":null,"logoUrl":null},{"id":2339,"code":"5100","label":"Software","bfoId":null,"name":"Programmatūra","position":null,"names":null,"selected":null,"createdBy":null,"createdOn":null,"updatedBy":null,"updatedOn":null,"usedBy":null,"bfoValidationState":null,"typeName":null,"ignored":false,"preferred":null,"logoUrl":null}],"certification":[{"id":117,"code":"WW-CERT-FOXBORO","label":null,"bfoId":null,"name":"WW-CERT-FOXBORO","position":null,"names":null,"selected":null,"createdBy":null,"createdOn":null,"updatedBy":null,"updatedOn":null,"usedBy":null,"bfoValidationState":null,"typeName":null,"ignored":false,"preferred":null,"logoUrl":null}],"associatedBrand":[],"competence":[],"openingHoursType":"NOT_SET","openingHours":[],"programGroups":[],"programLevels":[],"programs":[]}