[{"accountBfoId":"001A000000hy9t0IAA","id":345650,"active":null,"country":"Czech Republic","companyName":"Elektrocentrum ZNOJMO 95 s.r.o.","address1":"Dobšická 3697/6","address2":null,"zipCode":"669 02","city":"Znojmo","phone":null,"email":null,"webSite":"www.e-centrum.cz","webSite2":null,"createdBy":null,"createdOn":null,"updatedBy":null,"updatedOn":null,"b2cPhoto":null,"countryId":132,"latitude":48.853622,"longitude":16.072681,"administrativeRegion":null,"stateId":null,"webshop":"www.eshop.jakub.cz","emailExists":true,"phoneExists":true,"openingHoursType":"NOT_SET","partnerDetails":{"firstName":null,"lastName":null,"partnerContact":{"email":"obchodzn@elektrozbozi.cz","phone":"515224574"},"about":null,"logoBase64":null,"photoUrl":null,"addressTemplate1":null,"addressTemplate2":null,"detailsAddressTemplate1":null,"detailsAddressTemplate2":null,"detailsAddressTemplate3":null,"descriptions":[{"id":null,"languageId":null,"description":null,"isDefault":true}]},"openingHours":[],"preferredMarketServe":[],"competence":[],"areaOfFocus":[],"programLevels":[],"eshop":false,"federatedId":null}]