[{"accountBfoId":"0011200001CdfscAAB","id":370390,"active":null,"country":"Russian Federation","companyName":"Спецэлектромонтаж","address1":"ул. Энтузиастов, 15","address2":null,"zipCode":"620017","city":"Екатеринбург","phone":null,"email":null,"webSite":null,"webSite2":null,"createdBy":null,"createdOn":null,"updatedBy":null,"updatedOn":null,"b2cPhoto":null,"countryId":58,"latitude":56.892876,"longitude":60.62073,"administrativeRegion":null,"stateId":null,"webshop":null,"emailExists":false,"phoneExists":true,"openingHoursType":"NOT_SET","partnerDetails":{"firstName":null,"lastName":null,"partnerContact":{"email":null,"phone":"+7 965-537-88-28"},"about":"ООО 'СЭМ'                       Пн.-Пт 09:00-18:00","logoBase64":null,"photoUrl":null,"addressTemplate1":null,"addressTemplate2":null,"detailsAddressTemplate1":null,"detailsAddressTemplate2":null,"detailsAddressTemplate3":null,"descriptions":[{"id":null,"languageId":null,"description":"ООО 'СЭМ'                       Пн.-Пт 09:00-18:00","isDefault":true}]},"openingHours":[],"preferredMarketServe":[],"competence":[],"areaOfFocus":[],"programLevels":[],"eshop":null,"federatedId":null}]