[{"accountBfoId":"0011200001HOmDYAA1","id":507011,"active":null,"country":"Russian Federation","companyName":"СЕЛС Электрик","address1":"Юрия Гагарина, 7","address2":null,"zipCode":"450099","city":"г. Уфа","phone":null,"email":null,"webSite":null,"webSite2":null,"createdBy":null,"createdOn":null,"updatedBy":null,"updatedOn":null,"b2cPhoto":null,"countryId":58,"latitude":54.765,"longitude":56.054317,"administrativeRegion":"Republ.of Bashkortos","stateId":1616,"webshop":null,"emailExists":true,"phoneExists":true,"openingHoursType":"NOT_SET","partnerDetails":{"firstName":null,"lastName":null,"partnerContact":{"email":"celc-el@yandex.ru","phone":"+7 (347) 234 10 73"},"about":"И.П. Комлев Пн-Пт. 9.00-20.00,","logoBase64":null,"photoUrl":null,"addressTemplate1":null,"addressTemplate2":null,"detailsAddressTemplate1":null,"detailsAddressTemplate2":null,"detailsAddressTemplate3":null,"descriptions":[{"id":null,"languageId":null,"description":"И.П. Комлев Пн-Пт. 9.00-20.00,","isDefault":true}]},"openingHours":[],"preferredMarketServe":[],"competence":[],"areaOfFocus":[],"programLevels":[],"eshop":false,"federatedId":null}]