[{"accountBfoId":"001A000000eAKnxIAG","id":353314,"active":null,"country":"Russian Federation","companyName":"Минимакс","address1":"ул. Южная, д. 7","address2":null,"zipCode":"346892","city":"Батайск","phone":null,"email":null,"webSite":"www.minimaks.ru","webSite2":null,"createdBy":null,"createdOn":null,"updatedBy":null,"updatedOn":null,"b2cPhoto":null,"countryId":58,"latitude":47.1351,"longitude":39.73378,"administrativeRegion":"The Rostov Area","stateId":1670,"webshop":null,"emailExists":true,"phoneExists":true,"openingHoursType":"NOT_SET","partnerDetails":{"firstName":null,"lastName":null,"partnerContact":{"email":"direktor@mmrostov.ru","phone":"(86354) 5-78-51; (863) 280-06-37/38"},"about":"ПН-СБ: 9.00-18.00; ВС: выходной","logoBase64":null,"photoUrl":null,"addressTemplate1":null,"addressTemplate2":null,"detailsAddressTemplate1":null,"detailsAddressTemplate2":null,"detailsAddressTemplate3":null,"descriptions":[{"id":null,"languageId":null,"description":"ПН-СБ: 9.00-18.00; ВС: выходной","isDefault":true}]},"openingHours":[],"preferredMarketServe":[],"competence":[],"areaOfFocus":[],"programLevels":[],"eshop":false,"federatedId":null}]