[{"accountBfoId":"001A000000skxhnIAA","id":331339,"active":null,"country":"Italy","companyName":"DI.M.EL. SRL FORNITURE ELETTRICHE","address1":"VIA CAGLIARI 397","address2":null,"zipCode":"09170","city":"ORISTANO","phone":null,"email":null,"webSite":null,"webSite2":null,"createdBy":null,"createdOn":null,"updatedBy":null,"updatedOn":null,"b2cPhoto":null,"countryId":176,"latitude":39.893803,"longitude":8.597631,"administrativeRegion":null,"stateId":null,"webshop":null,"emailExists":false,"phoneExists":true,"openingHoursType":"NOT_SET","partnerDetails":{"firstName":null,"lastName":null,"partnerContact":{"email":null,"phone":"0783-303368"},"about":null,"logoBase64":null,"photoUrl":null,"addressTemplate1":null,"addressTemplate2":null,"detailsAddressTemplate1":null,"detailsAddressTemplate2":null,"detailsAddressTemplate3":null,"descriptions":[{"id":null,"languageId":null,"description":null,"isDefault":true}]},"openingHours":[],"preferredMarketServe":[],"competence":[],"areaOfFocus":[],"programLevels":[],"eshop":null,"federatedId":null}]