{"id":354156,"companyName":"PT Sentratek Metalindo.","address1":"Jl. Dr Cipto No.5, Surabaya 60264","address2":null,"zipCode":"1203","city":"Surabaya","administrativeRegion":"Jawa Timur","country":"Indonesia","countryId":213,"administrativeRegionId":1130,"webSite":"www.ptsentratekmetalindo.com","webSite2":null,"emailExists":true,"phoneExists":true,"latitude":-7.281287,"longitude":112.739105,"accountBfoId":"001A000000tR6FWIA0","webShop":null,"active":true,"type":null,"isFromBfo":true,"eshop":false,"federatedId":"6372c85d-e7f5-4598-a8f5-ae361dc5921f","partnerDetails":{"firstName":null,"lastName":null,"partnerContact":{"email":"marketing@sentratekmetalindo.com","phone":"031-5632100 5635014-17"},"about":"MV equipment distributor","logoBase64":null,"photoUrl":null,"addressTemplate1":"${ct}","addressTemplate2":"","detailsAddressTemplate1":"${ad}${ca}","detailsAddressTemplate2":"${cp}${ct}${bfoSt}${con}","detailsAddressTemplate3":"","descriptions":[{"id":4433,"languageId":176,"description":"MV equipment distributor","isDefault":true}]},"areaOfFocus":[{"id":70,"code":"WD2","label":"Electrical&IndustrialAutomationDistributor","bfoId":null,"name":"Elektriskās rūpniecības automatizācijas izplatītājs ","position":null,"names":null,"selected":null,"createdBy":null,"createdOn":null,"updatedBy":null,"updatedOn":null,"usedBy":null,"bfoValidationState":null,"typeName":null,"ignored":false,"preferred":null,"logoUrl":null}],"businessType":[{"id":12,"code":"WD","label":"B2B Distribution","bfoId":null,"name":"Izplatītāji","position":null,"names":null,"selected":null,"createdBy":null,"createdOn":null,"updatedBy":null,"updatedOn":null,"usedBy":null,"bfoValidationState":null,"typeName":null,"ignored":false,"preferred":null,"logoUrl":null}],"domainOfExpertise":[],"marketServe":[],"preferredMarketServe":[],"specialization":[{"id":2357,"code":"1900","label":"Feeder Automation","bfoId":null,"name":"Barotājlīniju automatizācija","position":null,"names":null,"selected":null,"createdBy":null,"createdOn":null,"updatedBy":null,"updatedOn":null,"usedBy":null,"bfoValidationState":null,"typeName":null,"ignored":false,"preferred":null,"logoUrl":null},{"id":2359,"code":"4600","label":"Protection Relays by Application","bfoId":null,"name":"Aizsargreleji pēc to lietojuma","position":null,"names":null,"selected":null,"createdBy":null,"createdOn":null,"updatedBy":null,"updatedOn":null,"usedBy":null,"bfoValidationState":null,"typeName":null,"ignored":false,"preferred":null,"logoUrl":null},{"id":2360,"code":"4700","label":"Protection Relays by Range","bfoId":null,"name":"Aizsargreleji pēc to klasifikācijas","position":null,"names":null,"selected":null,"createdBy":null,"createdOn":null,"updatedBy":null,"updatedOn":null,"usedBy":null,"bfoValidationState":null,"typeName":null,"ignored":false,"preferred":null,"logoUrl":null},{"id":2336,"code":"87897","label":"Medium Voltage Switchgear","bfoId":null,"name":"Vidējā Sprieguma Slēgiekārta","position":null,"names":null,"selected":null,"createdBy":null,"createdOn":null,"updatedBy":null,"updatedOn":null,"usedBy":null,"bfoValidationState":null,"typeName":null,"ignored":false,"preferred":null,"logoUrl":null},{"id":2337,"code":"3600","label":"Medium-Voltage Transformers","bfoId":null,"name":"VS transformatori","position":null,"names":null,"selected":null,"createdBy":null,"createdOn":null,"updatedBy":null,"updatedOn":null,"usedBy":null,"bfoValidationState":null,"typeName":null,"ignored":false,"preferred":null,"logoUrl":null},{"id":2354,"code":"88025","label":"Switchgear Components","bfoId":null,"name":"Slēgiekārtu Komponentes","position":null,"names":null,"selected":null,"createdBy":null,"createdOn":null,"updatedBy":null,"updatedOn":null,"usedBy":null,"bfoValidationState":null,"typeName":null,"ignored":false,"preferred":null,"logoUrl":null}],"certification":[],"associatedBrand":[],"competence":[],"openingHoursType":"NOT_SET","openingHours":[],"programGroups":[],"programLevels":[],"programs":[]}