[{"accountBfoId":"0011200001Cr8JOAAZ","id":328247,"active":null,"country":"Colombia","companyName":"EL FARO ELECTRICO","address1":"CARRERA 16 # 11 - 77","address2":null,"zipCode":null,"city":"Duitama","phone":null,"email":null,"webSite":null,"webSite2":null,"createdBy":null,"createdOn":null,"updatedBy":null,"updatedOn":null,"b2cPhoto":null,"countryId":118,"latitude":5.825913,"longitude":-73.036194,"administrativeRegion":"BOYACA","stateId":693,"webshop":null,"emailExists":true,"phoneExists":true,"openingHoursType":"NOT_SET","partnerDetails":{"firstName":null,"lastName":null,"partnerContact":{"email":"ventasduitama@elfaroelectrico.com","phone":"+57 8 7623268"},"about":null,"logoBase64":null,"photoUrl":null,"addressTemplate1":null,"addressTemplate2":null,"detailsAddressTemplate1":null,"detailsAddressTemplate2":null,"detailsAddressTemplate3":null,"descriptions":[{"id":null,"languageId":null,"description":null,"isDefault":true}]},"openingHours":[],"preferredMarketServe":[],"competence":[],"areaOfFocus":[],"programLevels":[],"eshop":false,"federatedId":null}]