[{"accountBfoId":"001A000000uux5yIAA","id":388840,"active":null,"country":"Poland","companyName":"El Sklad Sp. j.","address1":"Grunwaldzka 46","address2":null,"zipCode":"44-200","city":"Rybnik","phone":null,"email":null,"webSite":null,"webSite2":null,"createdBy":null,"createdOn":null,"updatedBy":null,"updatedOn":null,"b2cPhoto":null,"countryId":87,"latitude":50.094757,"longitude":18.520048,"administrativeRegion":"Slaskie","stateId":1518,"webshop":null,"emailExists":false,"phoneExists":true,"openingHoursType":"NOT_SET","partnerDetails":{"firstName":null,"lastName":null,"partnerContact":{"email":null,"phone":"+48324236457"},"about":null,"logoBase64":null,"photoUrl":null,"addressTemplate1":null,"addressTemplate2":null,"detailsAddressTemplate1":null,"detailsAddressTemplate2":null,"detailsAddressTemplate3":null,"descriptions":[{"id":null,"languageId":null,"description":null,"isDefault":true}]},"openingHours":[],"preferredMarketServe":[],"competence":[],"areaOfFocus":[],"programLevels":[],"eshop":false,"federatedId":null}]