[{"accountBfoId":"001A000000hzGnEIAU","id":356901,"active":null,"country":"Panama","companyName":"BTU ENERGIA S.A.","address1":"Panamá Viejo, edificio Business Center oficina 32-1","address2":null,"zipCode":"PA","city":null,"phone":null,"email":null,"webSite":"http://www.btupanama.com","webSite2":null,"createdBy":null,"createdOn":null,"updatedBy":null,"updatedOn":null,"b2cPhoto":null,"countryId":75,"latitude":8.982379,"longitude":-79.51987,"administrativeRegion":null,"stateId":null,"webshop":null,"emailExists":true,"phoneExists":true,"openingHoursType":"NOT_SET","partnerDetails":{"firstName":"Emilio","lastName":"Kourany","partnerContact":{"email":"ekourany@btupanama.com","phone":"507-399-4770"},"about":null,"logoBase64":null,"photoUrl":null,"addressTemplate1":null,"addressTemplate2":null,"detailsAddressTemplate1":null,"detailsAddressTemplate2":null,"detailsAddressTemplate3":null,"descriptions":[{"id":null,"languageId":null,"description":null,"isDefault":true}]},"openingHours":[],"preferredMarketServe":[],"competence":[],"areaOfFocus":[],"programLevels":[{"id":null,"code":null,"label":null,"bfoId":null,"name":null,"position":null,"names":null,"selected":null,"createdBy":null,"createdOn":null,"updatedBy":null,"updatedOn":null,"usedBy":null,"bfoValidationState":null,"typeName":null,"ignored":null,"preferred":null,"logoUrl":"images/program-levels_5426_1627543688927.jpg","displayRank":5,"global":null,"countryId":null,"countryLabel":null,"active":null,"programId":null,"program":null,"bfoLastData":null,"countryProgramLevels":null,"specializations":null,"globalProgramLevelId":null,"b2cAvailable":false},{"id":null,"code":null,"label":null,"bfoId":null,"name":null,"position":null,"names":null,"selected":null,"createdBy":null,"createdOn":null,"updatedBy":null,"updatedOn":null,"usedBy":null,"bfoValidationState":null,"typeName":null,"ignored":null,"preferred":null,"logoUrl":"images/program-levels_5485_1634718849983.png","displayRank":5,"global":null,"countryId":null,"countryLabel":null,"active":null,"programId":null,"program":null,"bfoLastData":null,"countryProgramLevels":null,"specializations":null,"globalProgramLevelId":null,"b2cAvailable":false}],"eshop":false,"federatedId":null}]