{"id":371854,"companyName":"Kiss László ev.  Műszaki Kereskedő","address1":"Mikes K. u. 38","address2":null,"zipCode":"3300","city":"Eger","administrativeRegion":null,"country":"Hungary","countryId":211,"administrativeRegionId":null,"webSite":null,"webSite2":null,"emailExists":false,"phoneExists":true,"latitude":47.902534,"longitude":20.377228,"accountBfoId":"001A000000k1cF4IAI","webShop":null,"active":true,"type":null,"isFromBfo":true,"eshop":null,"federatedId":null,"partnerDetails":{"firstName":null,"lastName":null,"partnerContact":{"email":null,"phone":"3636515412"},"about":null,"logoBase64":null,"photoUrl":null,"addressTemplate1":"${ct}","addressTemplate2":"","detailsAddressTemplate1":"${ad}${ca}","detailsAddressTemplate2":"${cp}${ct}${bfoSt}${con}","detailsAddressTemplate3":"","descriptions":[]},"areaOfFocus":[{"id":484,"code":"RTF","label":"Electrical Material Store","bfoId":null,"name":"Electrical Material Store","position":null,"names":null,"selected":null,"createdBy":null,"createdOn":null,"updatedBy":null,"updatedOn":null,"usedBy":null,"bfoValidationState":null,"typeName":null,"ignored":false,"preferred":null,"logoUrl":null}],"businessType":[{"id":8,"code":"RT","label":"Consumer Retailer","bfoId":null,"name":"Mazumtirgotāji","position":null,"names":null,"selected":null,"createdBy":null,"createdOn":null,"updatedBy":null,"updatedOn":null,"usedBy":null,"bfoValidationState":null,"typeName":null,"ignored":false,"preferred":null,"logoUrl":null}],"domainOfExpertise":[],"marketServe":[],"preferredMarketServe":[],"specialization":[],"certification":[],"associatedBrand":[],"competence":[],"openingHoursType":"NOT_SET","openingHours":[],"programGroups":[],"programLevels":[],"programs":[]}