{"partnerLocations":[{"id":332961,"latitude":-23.49654,"longitude":-46.54983,"countryId":135},{"id":318281,"latitude":-19.760069,"longitude":-47.939926,"countryId":135},{"id":430207,"latitude":-23.523087,"longitude":-46.196987,"countryId":135},{"id":318561,"latitude":-22.915966,"longitude":-47.042503,"countryId":135},{"id":388694,"latitude":-30.011185,"longitude":-51.200035,"countryId":135},{"id":318473,"latitude":-30.009129,"longitude":-51.19957,"countryId":135},{"id":388693,"latitude":-29.994854,"longitude":-51.196846,"countryId":135},{"id":389990,"latitude":-25.507057,"longitude":-49.29856,"countryId":135},{"id":429987,"latitude":-29.768278,"longitude":-50.041588,"countryId":135},{"id":426755,"latitude":-16.65955,"longitude":-49.245903,"countryId":135},{"id":318387,"latitude":-25.5259,"longitude":-49.190964,"countryId":135},{"id":318438,"latitude":-22.881458,"longitude":-42.025852,"countryId":135},{"id":318246,"latitude":-16.675169,"longitude":-49.28021,"countryId":135},{"id":431099,"latitude":-16.669088,"longitude":-49.273884,"countryId":135},{"id":506989,"latitude":-27.204954,"longitude":-49.619747,"countryId":135},{"id":318442,"latitude":-5.8663807,"longitude":-35.20535,"countryId":135},{"id":506990,"latitude":-28.596472,"longitude":-49.323658,"countryId":135},{"id":318396,"latitude":-25.51,"longitude":-54.6,"countryId":135},{"id":332955,"latitude":-22.855457,"longitude":-47.136047,"countryId":135},{"id":318238,"latitude":-20.287811,"longitude":-40.305832,"countryId":135},{"id":318648,"latitude":-14.793675,"longitude":-39.052586,"countryId":135},{"id":387873,"latitude":-22.889534,"longitude":-43.28722,"countryId":135},{"id":431343,"latitude":-19.87009,"longitude":-44.996395,"countryId":135},{"id":430707,"latitude":-22.5904,"longitude":-46.076008,"countryId":135},{"id":318796,"latitude":-22.423445,"longitude":-46.82615,"countryId":135},{"id":429207,"latitude":-25.1,"longitude":-50.11,"countryId":135},{"id":318636,"latitude":-3.0931218,"longitude":-60.013535,"countryId":135},{"id":354133,"latitude":-12.3305855,"longitude":-38.76718,"countryId":135},{"id":318319,"latitude":-18.594227,"longitude":-46.519096,"countryId":135},{"id":318581,"latitude":-22.290707,"longitude":-48.56162,"countryId":135},{"id":318481,"latitude":-27.591265,"longitude":-48.54069,"countryId":135},{"id":318292,"latitude":-21.688156,"longitude":-43.43466,"countryId":135},{"id":318533,"latitude":-23.705248,"longitude":-46.56833,"countryId":135},{"id":318510,"latitude":-20.800694,"longitude":-49.358208,"countryId":135},{"id":318465,"latitude":-29.164368,"longitude":-51.51252,"countryId":135},{"id":430206,"latitude":-23.289375,"longitude":-47.67759,"countryId":135},{"id":353958,"latitude":-16.713726,"longitude":-49.281685,"countryId":135},{"id":355770,"latitude":-23.707972,"longitude":-46.607605,"countryId":135},{"id":318420,"latitude":-22.793198,"longitude":-43.28714,"countryId":135},{"id":318590,"latitude":-22.918833,"longitude":-47.107964,"countryId":135},{"id":318518,"latitude":-23.549276,"longitude":-46.52442,"countryId":135},{"id":488769,"latitude":-22.757359,"longitude":-47.401142,"countryId":135},{"id":318577,"latitude":-22.918344,"longitude":-47.05461,"countryId":135},{"id":318229,"latitude":-20.847687,"longitude":-41.14027,"countryId":135},{"id":318435,"latitude":-22.407991,"longitude":-42.964245,"countryId":135},{"id":434055,"latitude":-3.7314296,"longitude":-38.546227,"countryId":135},{"id":318514,"latitude":-24.318544,"longitude":-46.994324,"countryId":135},{"id":318375,"latitude":-25.452393,"longitude":-49.25516,"countryId":135},{"id":318343,"latitude":-15.583777,"longitude":-56.093433,"countryId":135},{"id":318291,"latitude":-19.740686,"longitude":-45.256325,"countryId":135},{"id":318333,"latitude":-20.731602,"longitude":-46.60577,"countryId":135},{"id":324081,"latitude":-23.537003,"longitude":-46.641098,"countryId":135},{"id":318277,"latitude":-19.867613,"longitude":-43.903763,"countryId":135},{"id":318793,"latitude":-22.896254,"longitude":-43.240166,"countryId":135},{"id":318449,"latitude":-31.77,"longitude":-52.35,"countryId":135},{"id":318538,"latitude":-23.49983,"longitude":-46.87676,"countryId":135},{"id":318224,"latitude":-15.804111,"longitude":-47.949223,"countryId":135},{"id":318466,"latitude":-29.17,"longitude":-51.17,"countryId":135},{"id":332931,"latitude":-22.89259,"longitude":-43.22186,"countryId":135},{"id":318308,"latitude":-20.254393,"longitude":-43.800804,"countryId":135},{"id":429261,"latitude":-29.166935,"longitude":-51.191025,"countryId":135},{"id":318534,"latitude":-23.203285,"longitude":-46.889214,"countryId":135},{"id":318477,"latitude":-27.095457,"longitude":-52.629955,"countryId":135},{"id":318336,"latitude":-21.785685,"longitude":-46.564632,"countryId":135},{"id":318452,"latitude":-29.992498,"longitude":-51.11632,"countryId":135},{"id":318286,"latitude":-19.869133,"longitude":-47.440327,"countryId":135},{"id":332958,"latitude":-23.460327,"longitude":-46.500908,"countryId":135},{"id":332879,"latitude":-20.255993,"longitude":-40.26849,"countryId":135},{"id":318546,"latitude":-22.88214,"longitude":-47.062126,"countryId":135},{"id":318349,"latitude":-1.1950407,"longitude":-47.173622,"countryId":135},{"id":427751,"latitude":-22.67385,"longitude":-47.63198,"countryId":135},{"id":318560,"latitude":-22.549816,"longitude":-47.915543,"countryId":135},{"id":318263,"latitude":-18.913633,"longitude":-48.28224,"countryId":135},{"id":318392,"latitude":-24.966326,"longitude":-53.467403,"countryId":135},{"id":431623,"latitude":-22.846954,"longitude":-47.08585,"countryId":135},{"id":431624,"latitude":-25.44553,"longitude":-49.28636,"countryId":135},{"id":318503,"latitude":-23.526037,"longitude":-46.734272,"countryId":135},{"id":332909,"latitude":-8.223185,"longitude":-34.96642,"countryId":135},{"id":332914,"latitude":-25.483969,"longitude":-49.26121,"countryId":135},{"id":318295,"latitude":-18.946241,"longitude":-48.235,"countryId":135},{"id":318309,"latitude":-19.770508,"longitude":-47.951363,"countryId":135},{"id":318311,"latitude":-19.769823,"longitude":-47.92421,"countryId":135},{"id":318485,"latitude":-26.492216,"longitude":-49.080544,"countryId":135},{"id":318500,"latitude":-20.261147,"longitude":-50.539467,"countryId":135},{"id":429992,"latitude":-29.296736,"longitude":-51.501225,"countryId":135},{"id":388695,"latitude":-30.012476,"longitude":-51.197495,"countryId":135},{"id":318429,"latitude":-22.830517,"longitude":-42.08728,"countryId":135},{"id":429991,"latitude":-29.260405,"longitude":-51.52351,"countryId":135},{"id":420120,"latitude":-21.69822,"longitude":-43.42519,"countryId":135},{"id":318235,"latitude":-20.346302,"longitude":-40.28763,"countryId":135},{"id":428660,"latitude":-28.749893,"longitude":-49.473907,"countryId":135},{"id":318323,"latitude":-22.556734,"longitude":-45.78083,"countryId":135},{"id":318239,"latitude":-20.341673,"longitude":-40.309467,"countryId":135},{"id":318790,"latitude":-24.955177,"longitude":-53.455215,"countryId":135},{"id":318347,"latitude":-15.546318,"longitude":-54.295307,"countryId":135},{"id":318430,"latitude":-22.881252,"longitude":-42.02194,"countryId":135},{"id":318536,"latitude":-22.770525,"longitude":-47.154343,"countryId":135},{"id":318563,"latitude":-21.174438,"longitude":-47.804367,"countryId":135},{"id":318549,"latitude":-21.931915,"longitude":-50.513092,"countryId":135},{"id":318586,"latitude":-23.644115,"longitude":-46.55486,"countryId":135},{"id":429187,"latitude":-3.13,"longitude":-60.0,"countryId":135},{"id":318424,"latitude":-22.887115,"longitude":-43.12077,"countryId":135},{"id":318565,"latitude":-21.209751,"longitude":-50.438564,"countryId":135},{"id":428945,"latitude":-25.482296,"longitude":-49.31605,"countryId":135},{"id":428581,"latitude":-3.790416,"longitude":-38.51726,"countryId":135},{"id":387310,"latitude":-12.876494,"longitude":-38.29796,"countryId":135},{"id":428656,"latitude":-26.247093,"longitude":-48.862255,"countryId":135},{"id":332922,"latitude":-23.419325,"longitude":-51.913094,"countryId":135},{"id":332876,"latitude":-20.209751,"longitude":-40.260105,"countryId":135},{"id":387525,"latitude":-22.599504,"longitude":-47.379242,"countryId":135},{"id":428659,"latitude":-26.875898,"longitude":-49.117325,"countryId":135},{"id":318599,"latitude":-23.522388,"longitude":-46.66004,"countryId":135},{"id":318585,"latitude":-22.325008,"longitude":-49.04885,"countryId":135},{"id":332979,"latitude":-23.52106,"longitude":-46.728687,"countryId":135},{"id":318788,"latitude":-7.4385586,"longitude":-34.97726,"countryId":135},{"id":318450,"latitude":-29.723562,"longitude":-51.138397,"countryId":135},{"id":388510,"latitude":-21.210905,"longitude":-47.801052,"countryId":135},{"id":332980,"latitude":-22.936312,"longitude":-47.036568,"countryId":135},{"id":318310,"latitude":-16.723888,"longitude":-43.862946,"countryId":135},{"id":318413,"latitude":-22.371721,"longitude":-41.78573,"countryId":135},{"id":332878,"latitude":-20.20329,"longitude":-40.23479,"countryId":135},{"id":318537,"latitude":-22.735935,"longitude":-45.588005,"countryId":135},{"id":427757,"latitude":-7.2161045,"longitude":-35.890614,"countryId":135},{"id":318654,"latitude":-9.401502,"longitude":-38.222115,"countryId":135},{"id":318488,"latitude":-27.096607,"longitude":-48.933376,"countryId":135},{"id":318386,"latitude":-25.28748,"longitude":-54.089195,"countryId":135},{"id":318494,"latitude":-10.907112,"longitude":-37.059135,"countryId":135},{"id":318795,"latitude":-22.96401,"longitude":-46.54303,"countryId":135},{"id":318508,"latitude":-21.132042,"longitude":-48.972973,"countryId":135},{"id":431567,"latitude":-23.509563,"longitude":-46.70212,"countryId":135},{"id":318579,"latitude":-22.22765,"longitude":-49.94591,"countryId":135},{"id":318652,"latitude":-12.94,"longitude":-38.51,"countryId":135},{"id":354924,"latitude":-20.815535,"longitude":-49.365826,"countryId":135},{"id":318306,"latitude":-20.756578,"longitude":-42.87767,"countryId":135},{"id":318649,"latitude":-14.853641,"longitude":-40.85207,"countryId":135},{"id":318284,"latitude":-20.421267,"longitude":-42.905342,"countryId":135},{"id":318780,"latitude":-18.15609,"longitude":-47.932804,"countryId":135},{"id":332982,"latitude":-23.537748,"longitude":-46.639774,"countryId":135},{"id":332968,"latitude":-23.944212,"longitude":-46.326607,"countryId":135},{"id":332970,"latitude":-23.507036,"longitude":-46.668022,"countryId":135},{"id":427960,"latitude":-26.29327,"longitude":-48.879295,"countryId":135},{"id":332971,"latitude":-23.537647,"longitude":-46.63987,"countryId":135},{"id":327448,"latitude":-25.51,"longitude":-49.28,"countryId":135},{"id":332972,"latitude":-23.53668,"longitude":-46.64064,"countryId":135},{"id":332973,"latitude":-23.536781,"longitude":-46.64044,"countryId":135},{"id":318380,"latitude":-24.532722,"longitude":-54.05177,"countryId":135},{"id":318650,"latitude":-14.222015,"longitude":-42.78067,"countryId":135},{"id":318225,"latitude":-15.762736,"longitude":-47.888634,"countryId":135},{"id":386028,"latitude":-25.437716,"longitude":-49.17663,"countryId":135},{"id":318341,"latitude":-22.221611,"longitude":-54.754204,"countryId":135},{"id":318320,"latitude":-21.745152,"longitude":-43.366108,"countryId":135},{"id":318642,"latitude":-14.864775,"longitude":-40.836933,"countryId":135},{"id":318293,"latitude":-18.654064,"longitude":-48.187664,"countryId":135},{"id":318578,"latitude":-22.209038,"longitude":-49.95321,"countryId":135},{"id":420123,"latitude":-22.559744,"longitude":-47.425877,"countryId":135},{"id":429364,"latitude":-22.559656,"longitude":-47.426407,"countryId":135},{"id":318783,"latitude":-20.138878,"longitude":-44.900578,"countryId":135},{"id":318517,"latitude":-23.51396,"longitude":-46.693512,"countryId":135},{"id":318559,"latitude":-21.134798,"longitude":-47.999187,"countryId":135},{"id":428940,"latitude":-12.938721,"longitude":-38.50547,"countryId":135},{"id":318305,"latitude":-20.024206,"longitude":-45.540577,"countryId":135},{"id":364939,"latitude":-21.784307,"longitude":-43.360374,"countryId":135},{"id":318274,"latitude":-18.592308,"longitude":-46.524208,"countryId":135},{"id":318781,"latitude":-20.141058,"longitude":-44.905537,"countryId":135},{"id":318516,"latitude":-24.183527,"longitude":-46.790493,"countryId":135},{"id":318223,"latitude":-15.746931,"longitude":-47.92577,"countryId":135},{"id":387289,"latitude":-23.69304,"longitude":-46.622066,"countryId":135},{"id":318526,"latitude":-23.60555,"longitude":-47.020073,"countryId":135},{"id":388237,"latitude":-25.479517,"longitude":-49.201534,"countryId":135},{"id":430773,"latitude":-12.614101,"longitude":-38.302433,"countryId":135},{"id":430776,"latitude":-12.941172,"longitude":-38.50361,"countryId":135},{"id":318338,"latitude":-21.127354,"longitude":-44.246487,"countryId":135},{"id":504678,"latitude":-10.191425,"longitude":-48.32662,"countryId":135},{"id":388283,"latitude":-25.478,"longitude":-49.284874,"countryId":135},{"id":318399,"latitude":-23.300766,"longitude":-51.183147,"countryId":135},{"id":332905,"latitude":-7.286246,"longitude":-35.888416,"countryId":135},{"id":318259,"latitude":-19.952694,"longitude":-44.05079,"countryId":135},{"id":318346,"latitude":-15.620639,"longitude":-56.076363,"countryId":135},{"id":429031,"latitude":-23.676842,"longitude":-46.51075,"countryId":135},{"id":318403,"latitude":-23.299074,"longitude":-51.168045,"countryId":135},{"id":318782,"latitude":-21.762222,"longitude":-43.346527,"countryId":135},{"id":318531,"latitude":-23.270353,"longitude":-47.311203,"countryId":135},{"id":318548,"latitude":-22.296497,"longitude":-48.562023,"countryId":135},{"id":318398,"latitude":-23.42,"longitude":-51.95,"countryId":135},{"id":318539,"latitude":-23.254904,"longitude":-45.926876,"countryId":135},{"id":318800,"latitude":-20.818275,"longitude":-49.517754,"countryId":135},{"id":318298,"latitude":-19.30594,"longitude":-48.92449,"countryId":135},{"id":318289,"latitude":-18.97641,"longitude":-49.469948,"countryId":135},{"id":318301,"latitude":-21.25393,"longitude":-45.000793,"countryId":135},{"id":332903,"latitude":-1.4115669,"longitude":-48.471443,"countryId":135},{"id":318554,"latitude":-21.176165,"longitude":-47.80284,"countryId":135},{"id":430711,"latitude":-16.682442,"longitude":-49.281845,"countryId":135},{"id":386831,"latitude":-8.072426,"longitude":-34.907787,"countryId":135},{"id":429117,"latitude":-22.430082,"longitude":-45.461098,"countryId":135},{"id":318461,"latitude":-29.167688,"longitude":-51.167416,"countryId":135},{"id":318269,"latitude":-19.156769,"longitude":-45.443344,"countryId":135},{"id":332934,"latitude":-22.865358,"longitude":-43.249462,"countryId":135},{"id":318230,"latitude":-20.30164,"longitude":-40.303864,"countryId":135},{"id":318267,"latitude":-20.11458,"longitude":-44.89239,"countryId":135},{"id":318456,"latitude":-29.701727,"longitude":-53.81365,"countryId":135},{"id":318264,"latitude":-20.286285,"longitude":-45.538242,"countryId":135},{"id":332921,"latitude":-25.572964,"longitude":-49.386585,"countryId":135},{"id":332925,"latitude":-25.550076,"longitude":-49.196274,"countryId":135},{"id":318381,"latitude":-23.299852,"longitude":-51.187485,"countryId":135},{"id":332923,"latitude":-23.177038,"longitude":-50.65996,"countryId":135},{"id":332912,"latitude":-23.191996,"longitude":-50.6534,"countryId":135},{"id":318228,"latitude":-20.223412,"longitude":-40.287903,"countryId":135},{"id":318390,"latitude":-25.758873,"longitude":-53.06242,"countryId":135},{"id":431381,"latitude":-20.307758,"longitude":-40.302586,"countryId":135},{"id":430719,"latitude":-2.5597365,"longitude":-44.303944,"countryId":135},{"id":318397,"latitude":-25.54,"longitude":-54.58,"countryId":135},{"id":318337,"latitude":-19.879541,"longitude":-44.986824,"countryId":135},{"id":429172,"latitude":-27.59215,"longitude":-48.543293,"countryId":135},{"id":429173,"latitude":-20.81025,"longitude":-49.407867,"countryId":135},{"id":331889,"latitude":-23.609581,"longitude":-46.598785,"countryId":135},{"id":318457,"latitude":-28.268703,"longitude":-52.430046,"countryId":135},{"id":318312,"latitude":-21.77233,"longitude":-43.37272,"countryId":135},{"id":318342,"latitude":-20.478884,"longitude":-54.613026,"countryId":135},{"id":318551,"latitude":-22.148994,"longitude":-51.40278,"countryId":135},{"id":328224,"latitude":-22.664518,"longitude":-50.416607,"countryId":135},{"id":332929,"latitude":-22.82866,"longitude":-43.344357,"countryId":135},{"id":318233,"latitude":-20.299242,"longitude":-40.304558,"countryId":135},{"id":318646,"latitude":-12.969851,"longitude":-39.261738,"countryId":135},{"id":318232,"latitude":-20.3,"longitude":-40.3,"countryId":135},{"id":332930,"latitude":-22.27925,"longitude":-42.532402,"countryId":135},{"id":383102,"latitude":-8.221273,"longitude":-34.96247,"countryId":135},{"id":318401,"latitude":-23.55466,"longitude":-51.450394,"countryId":135},{"id":431342,"latitude":-19.96801,"longitude":-43.979187,"countryId":135},{"id":318283,"latitude":-21.762148,"longitude":-43.346172,"countryId":135},{"id":318515,"latitude":-23.944128,"longitude":-46.329506,"countryId":135},{"id":318792,"latitude":-25.510176,"longitude":-54.584423,"countryId":135},{"id":318418,"latitude":-22.983938,"longitude":-43.69508,"countryId":135},{"id":430774,"latitude":-12.879042,"longitude":-38.30854,"countryId":135},{"id":318647,"latitude":-12.671826,"longitude":-39.10403,"countryId":135},{"id":488775,"latitude":-20.567373,"longitude":-47.39342,"countryId":135},{"id":431386,"latitude":-20.294313,"longitude":-40.29251,"countryId":135},{"id":424433,"latitude":-23.496288,"longitude":-46.83035,"countryId":135},{"id":318791,"latitude":-23.761944,"longitude":-53.312256,"countryId":135},{"id":431106,"latitude":-22.897127,"longitude":-47.05053,"countryId":135},{"id":318395,"latitude":-25.432642,"longitude":-49.312813,"countryId":135},{"id":318434,"latitude":-22.291283,"longitude":-43.1175,"countryId":135},{"id":318594,"latitude":-23.979311,"longitude":-48.8769,"countryId":135},{"id":507001,"latitude":-15.799965,"longitude":-47.970444,"countryId":135},{"id":318254,"latitude":-2.5170262,"longitude":-44.304226,"countryId":135},{"id":332886,"latitude":-2.534193,"longitude":-44.26057,"countryId":135},{"id":332888,"latitude":-2.5682974,"longitude":-44.231762,"countryId":135},{"id":420124,"latitude":-29.165596,"longitude":-51.171093,"countryId":135},{"id":318300,"latitude":-21.883383,"longitude":-42.69851,"countryId":135},{"id":318794,"latitude":-21.77993,"longitude":-48.170235,"countryId":135},{"id":318389,"latitude":-23.66,"longitude":-52.62,"countryId":135},{"id":318569,"latitude":-21.202814,"longitude":-50.402397,"countryId":135},{"id":363659,"latitude":-23.010324,"longitude":-51.95075,"countryId":135},{"id":332978,"latitude":-23.035204,"longitude":-46.984882,"countryId":135},{"id":429175,"latitude":-16.369356,"longitude":-39.59109,"countryId":135},{"id":318353,"latitude":-7.2171717,"longitude":-35.88717,"countryId":135},{"id":505856,"latitude":-27.1742,"longitude":-51.49627,"countryId":135},{"id":318476,"latitude":-27.638678,"longitude":-48.66338,"countryId":135},{"id":429941,"latitude":-30.012093,"longitude":-51.197315,"countryId":135},{"id":318288,"latitude":-19.485476,"longitude":-46.54487,"countryId":135},{"id":428408,"latitude":-25.500336,"longitude":-49.279026,"countryId":135},{"id":318262,"latitude":-19.822641,"longitude":-43.902527,"countryId":135},{"id":318544,"latitude":-23.084492,"longitude":-47.213158,"countryId":135},{"id":372047,"latitude":-23.52993,"longitude":-46.205364,"countryId":135},{"id":318417,"latitude":-22.899593,"longitude":-43.225418,"countryId":135},{"id":431385,"latitude":-20.298758,"longitude":-40.303486,"countryId":135},{"id":318444,"latitude":-5.808992,"longitude":-35.225323,"countryId":135},{"id":429989,"latitude":-29.680897,"longitude":-51.129997,"countryId":135},{"id":388021,"latitude":-23.203472,"longitude":-46.890766,"countryId":135},{"id":429211,"latitude":-19.96846,"longitude":-44.07001,"countryId":135},{"id":361565,"latitude":-22.930511,"longitude":-43.36571,"countryId":135},{"id":350807,"latitude":-22.891066,"longitude":-43.532898,"countryId":135},{"id":318624,"latitude":-22.915476,"longitude":-47.060272,"countryId":135},{"id":488855,"latitude":-23.883879,"longitude":-46.421474,"countryId":135},{"id":332969,"latitude":-23.255331,"longitude":-45.927982,"countryId":135},{"id":318504,"latitude":-23.652752,"longitude":-46.53355,"countryId":135},{"id":387838,"latitude":-26.268404,"longitude":-48.85998,"countryId":135},{"id":387839,"latitude":-23.421474,"longitude":-51.97373,"countryId":135},{"id":389610,"latitude":-20.204172,"longitude":-40.305416,"countryId":135},{"id":318372,"latitude":-25.490091,"longitude":-49.27298,"countryId":135},{"id":318385,"latitude":-24.730404,"longitude":-53.73846,"countryId":135},{"id":318475,"latitude":-26.253626,"longitude":-49.38181,"countryId":135},{"id":318221,"latitude":-3.722842,"longitude":-38.534416,"countryId":135},{"id":318621,"latitude":-22.736082,"longitude":-47.335392,"countryId":135},{"id":332917,"latitude":-23.401577,"longitude":-51.42852,"countryId":135},{"id":332875,"latitude":-20.184551,"longitude":-40.23089,"countryId":135},{"id":318261,"latitude":-19.843126,"longitude":-43.953125,"countryId":135},{"id":332966,"latitude":-23.454153,"longitude":-46.502457,"countryId":135},{"id":332990,"latitude":-22.374771,"longitude":-46.97128,"countryId":135},{"id":318575,"latitude":-22.355293,"longitude":-46.94458,"countryId":135},{"id":318576,"latitude":-22.374456,"longitude":-46.94054,"countryId":135},{"id":332894,"latitude":-19.96996,"longitude":-44.06671,"countryId":135},{"id":429986,"latitude":-29.983421,"longitude":-51.11269,"countryId":135},{"id":429988,"latitude":-27.62452,"longitude":-48.642414,"countryId":135},{"id":430795,"latitude":-25.093563,"longitude":-50.16178,"countryId":135},{"id":354102,"latitude":-22.752562,"longitude":-43.481438,"countryId":135},{"id":318555,"latitude":-20.423027,"longitude":-49.974358,"countryId":135},{"id":388195,"latitude":-25.449078,"longitude":-49.28854,"countryId":135},{"id":332907,"latitude":-8.170324,"longitude":-34.939697,"countryId":135},{"id":332887,"latitude":-2.5567505,"longitude":-44.223583,"countryId":135},{"id":388212,"latitude":-6.050394,"longitude":-49.88207,"countryId":135},{"id":332977,"latitude":-21.185585,"longitude":-47.78476,"countryId":135},{"id":332883,"latitude":-16.66339,"longitude":-49.336536,"countryId":135},{"id":332975,"latitude":-22.98,"longitude":-47.11,"countryId":135},{"id":318268,"latitude":-19.875021,"longitude":-43.955036,"countryId":135},{"id":332987,"latitude":-22.89,"longitude":-47.06,"countryId":135},{"id":332939,"latitude":-29.909046,"longitude":-51.180588,"countryId":135},{"id":332877,"latitude":-20.177126,"longitude":-40.23558,"countryId":135},{"id":332945,"latitude":-26.262857,"longitude":-48.86765,"countryId":135},{"id":332999,"latitude":-12.889014,"longitude":-38.3276,"countryId":135},{"id":382530,"latitude":-19.93086,"longitude":-44.033623,"countryId":135},{"id":318623,"latitude":-23.655313,"longitude":-46.53209,"countryId":135},{"id":431380,"latitude":-19.536085,"longitude":-40.63062,"countryId":135},{"id":318789,"latitude":-23.50421,"longitude":-51.699024,"countryId":135},{"id":318316,"latitude":-19.742208,"longitude":-45.275795,"countryId":135},{"id":332984,"latitude":-23.646837,"longitude":-46.663296,"countryId":135},{"id":324080,"latitude":-22.813904,"longitude":-47.278347,"countryId":135},{"id":318597,"latitude":-22.728107,"longitude":-47.306835,"countryId":135},{"id":332918,"latitude":-25.392664,"longitude":-51.457092,"countryId":135},{"id":318391,"latitude":-26.231136,"longitude":-52.67265,"countryId":135},{"id":430204,"latitude":-26.894104,"longitude":-48.677307,"countryId":135},{"id":318522,"latitude":-22.724682,"longitude":-47.646553,"countryId":135},{"id":318470,"latitude":-30.02,"longitude":-51.21,"countryId":135},{"id":389530,"latitude":-27.106081,"longitude":-52.62773,"countryId":135},{"id":332998,"latitude":-12.939093,"longitude":-38.50476,"countryId":135},{"id":318231,"latitude":-20.854658,"longitude":-41.118484,"countryId":135},{"id":318469,"latitude":-29.99162,"longitude":-51.142857,"countryId":135},{"id":333002,"latitude":-12.229855,"longitude":-38.962936,"countryId":135},{"id":318498,"latitude":-22.726463,"longitude":-47.641964,"countryId":135},{"id":429209,"latitude":-22.973156,"longitude":-43.36646,"countryId":135},{"id":370817,"latitude":-25.458733,"longitude":-49.2175,"countryId":135},{"id":430796,"latitude":-25.534582,"longitude":-49.203266,"countryId":135},{"id":332992,"latitude":-22.682217,"longitude":-47.673252,"countryId":135},{"id":318639,"latitude":-3.125,"longitude":-59.988678,"countryId":135},{"id":420119,"latitude":-24.465223,"longitude":-53.953835,"countryId":135},{"id":318610,"latitude":-22.99573,"longitude":-47.49663,"countryId":135},{"id":353959,"latitude":-15.614746,"longitude":-56.115685,"countryId":135},{"id":332965,"latitude":-23.631731,"longitude":-46.55695,"countryId":135},{"id":385233,"latitude":-26.31314,"longitude":-48.845413,"countryId":135},{"id":318798,"latitude":-23.536861,"longitude":-46.640194,"countryId":135},{"id":332952,"latitude":-23.52648,"longitude":-46.792046,"countryId":135},{"id":429943,"latitude":-29.334267,"longitude":-49.734493,"countryId":135},{"id":318354,"latitude":-7.217412,"longitude":-35.886642,"countryId":135},{"id":430797,"latitude":-25.46877,"longitude":-49.34903,"countryId":135},{"id":332944,"latitude":-26.99329,"longitude":-48.642494,"countryId":135},{"id":318492,"latitude":-28.679602,"longitude":-49.341236,"countryId":135},{"id":356498,"latitude":-27.556377,"longitude":-48.624237,"countryId":135},{"id":428526,"latitude":-18.732235,"longitude":-39.75543,"countryId":135},{"id":429208,"latitude":-29.659822,"longitude":-51.176327,"countryId":135},{"id":318220,"latitude":-3.73,"longitude":-38.55,"countryId":135},{"id":505774,"latitude":-3.1190276,"longitude":-60.021732,"countryId":135},{"id":505775,"latitude":-3.106079,"longitude":-60.059994,"countryId":135},{"id":318502,"latitude":-21.301111,"longitude":-50.360332,"countryId":135},{"id":318249,"latitude":-18.417543,"longitude":-49.22779,"countryId":135},{"id":318304,"latitude":-21.409834,"longitude":-50.07258,"countryId":135},{"id":488776,"latitude":-21.198421,"longitude":-47.778168,"countryId":135},{"id":488777,"latitude":-23.415545,"longitude":-51.92409,"countryId":135},{"id":426932,"latitude":-23.209509,"longitude":-46.878788,"countryId":135},{"id":318622,"latitude":-23.528915,"longitude":-46.646996,"countryId":135},{"id":318520,"latitude":-22.821615,"longitude":-47.266438,"countryId":135},{"id":332976,"latitude":-20.948484,"longitude":-48.48134,"countryId":135},{"id":318297,"latitude":-19.757877,"longitude":-47.942627,"countryId":135},{"id":430720,"latitude":-19.874382,"longitude":-44.022408,"countryId":135},{"id":332899,"latitude":-20.386652,"longitude":-43.42488,"countryId":135},{"id":318556,"latitude":-23.31191,"longitude":-45.982464,"countryId":135},{"id":318541,"latitude":-23.196169,"longitude":-45.88715,"countryId":135},{"id":318595,"latitude":-23.022327,"longitude":-45.546196,"countryId":135},{"id":431066,"latitude":-19.884548,"longitude":-43.96178,"countryId":135},{"id":318542,"latitude":-23.29455,"longitude":-45.957584,"countryId":135},{"id":429210,"latitude":-26.91,"longitude":-49.07,"countryId":135},{"id":431506,"latitude":-12.923447,"longitude":-38.388046,"countryId":135},{"id":318501,"latitude":-22.739738,"longitude":-47.66492,"countryId":135},{"id":431530,"latitude":-29.438652,"longitude":-51.974007,"countryId":135},{"id":427957,"latitude":-29.029812,"longitude":-51.18359,"countryId":135},{"id":428661,"latitude":-27.062912,"longitude":-48.89902,"countryId":135},{"id":318382,"latitude":-23.308748,"longitude":-51.170307,"countryId":135},{"id":429203,"latitude":-23.62,"longitude":-46.69,"countryId":135},{"id":332967,"latitude":-23.482788,"longitude":-46.746014,"countryId":135},{"id":389307,"latitude":-29.18685,"longitude":-51.199905,"countryId":135},{"id":332964,"latitude":-23.490965,"longitude":-46.624706,"countryId":135}],"references":{"programsType":null,"businessType":[],"areaOfFocus":[],"associatedBrand":[],"certification":[],"domainOfExpertise":[],"marketServe":[],"specialization":[{"id":2374,"code":null,"label":null,"bfoId":null,"name":null,"position":null,"names":null,"selected":null,"createdBy":null,"createdOn":null,"updatedBy":null,"updatedOn":null,"usedBy":null,"bfoValidationState":null,"typeName":null,"ignored":null,"preferred":null,"logoUrl":null},{"id":2375,"code":null,"label":null,"bfoId":null,"name":null,"position":null,"names":null,"selected":null,"createdBy":null,"createdOn":null,"updatedBy":null,"updatedOn":null,"usedBy":null,"bfoValidationState":null,"typeName":null,"ignored":null,"preferred":null,"logoUrl":null},{"id":2376,"code":null,"label":null,"bfoId":null,"name":null,"position":null,"names":null,"selected":null,"createdBy":null,"createdOn":null,"updatedBy":null,"updatedOn":null,"usedBy":null,"bfoValidationState":null,"typeName":null,"ignored":null,"preferred":null,"logoUrl":null},{"id":2384,"code":null,"label":null,"bfoId":null,"name":null,"position":null,"names":null,"selected":null,"createdBy":null,"createdOn":null,"updatedBy":null,"updatedOn":null,"usedBy":null,"bfoValidationState":null,"typeName":null,"ignored":null,"preferred":null,"logoUrl":null},{"id":2386,"code":null,"label":null,"bfoId":null,"name":null,"position":null,"names":null,"selected":null,"createdBy":null,"createdOn":null,"updatedBy":null,"updatedOn":null,"usedBy":null,"bfoValidationState":null,"typeName":null,"ignored":null,"preferred":null,"logoUrl":null},{"id":2387,"code":null,"label":null,"bfoId":null,"name":null,"position":null,"names":null,"selected":null,"createdBy":null,"createdOn":null,"updatedBy":null,"updatedOn":null,"usedBy":null,"bfoValidationState":null,"typeName":null,"ignored":null,"preferred":null,"logoUrl":null},{"id":2388,"code":null,"label":null,"bfoId":null,"name":null,"position":null,"names":null,"selected":null,"createdBy":null,"createdOn":null,"updatedBy":null,"updatedOn":null,"usedBy":null,"bfoValidationState":null,"typeName":null,"ignored":null,"preferred":null,"logoUrl":null},{"id":2390,"code":null,"label":null,"bfoId":null,"name":null,"position":null,"names":null,"selected":null,"createdBy":null,"createdOn":null,"updatedBy":null,"updatedOn":null,"usedBy":null,"bfoValidationState":null,"typeName":null,"ignored":null,"preferred":null,"logoUrl":null},{"id":2391,"code":null,"label":null,"bfoId":null,"name":null,"position":null,"names":null,"selected":null,"createdBy":null,"createdOn":null,"updatedBy":null,"updatedOn":null,"usedBy":null,"bfoValidationState":null,"typeName":null,"ignored":null,"preferred":null,"logoUrl":null},{"id":2392,"code":null,"label":null,"bfoId":null,"name":null,"position":null,"names":null,"selected":null,"createdBy":null,"createdOn":null,"updatedBy":null,"updatedOn":null,"usedBy":null,"bfoValidationState":null,"typeName":null,"ignored":null,"preferred":null,"logoUrl":null},{"id":2313,"code":null,"label":null,"bfoId":null,"name":null,"position":null,"names":null,"selected":null,"createdBy":null,"createdOn":null,"updatedBy":null,"updatedOn":null,"usedBy":null,"bfoValidationState":null,"typeName":null,"ignored":null,"preferred":null,"logoUrl":null},{"id":2314,"code":null,"label":null,"bfoId":null,"name":null,"position":null,"names":null,"selected":null,"createdBy":null,"createdOn":null,"updatedBy":null,"updatedOn":null,"usedBy":null,"bfoValidationState":null,"typeName":null,"ignored":null,"preferred":null,"logoUrl":null},{"id":2315,"code":null,"label":null,"bfoId":null,"name":null,"position":null,"names":null,"selected":null,"createdBy":null,"createdOn":null,"updatedBy":null,"updatedOn":null,"usedBy":null,"bfoValidationState":null,"typeName":null,"ignored":null,"preferred":null,"logoUrl":null},{"id":2316,"code":null,"label":null,"bfoId":null,"name":null,"position":null,"names":null,"selected":null,"createdBy":null,"createdOn":null,"updatedBy":null,"updatedOn":null,"usedBy":null,"bfoValidationState":null,"typeName":null,"ignored":null,"preferred":null,"logoUrl":null},{"id":2317,"code":null,"label":null,"bfoId":null,"name":null,"position":null,"names":null,"selected":null,"createdBy":null,"createdOn":null,"updatedBy":null,"updatedOn":null,"usedBy":null,"bfoValidationState":null,"typeName":null,"ignored":null,"preferred":null,"logoUrl":null},{"id":2318,"code":null,"label":null,"bfoId":null,"name":null,"position":null,"names":null,"selected":null,"createdBy":null,"createdOn":null,"updatedBy":null,"updatedOn":null,"usedBy":null,"bfoValidationState":null,"typeName":null,"ignored":null,"preferred":null,"logoUrl":null},{"id":2319,"code":null,"label":null,"bfoId":null,"name":null,"position":null,"names":null,"selected":null,"createdBy":null,"createdOn":null,"updatedBy":null,"updatedOn":null,"usedBy":null,"bfoValidationState":null,"typeName":null,"ignored":null,"preferred":null,"logoUrl":null},{"id":2320,"code":null,"label":null,"bfoId":null,"name":null,"position":null,"names":null,"selected":null,"createdBy":null,"createdOn":null,"updatedBy":null,"updatedOn":null,"usedBy":null,"bfoValidationState":null,"typeName":null,"ignored":null,"preferred":null,"logoUrl":null},{"id":2322,"code":null,"label":null,"bfoId":null,"name":null,"position":null,"names":null,"selected":null,"createdBy":null,"createdOn":null,"updatedBy":null,"updatedOn":null,"usedBy":null,"bfoValidationState":null,"typeName":null,"ignored":null,"preferred":null,"logoUrl":null},{"id":2323,"code":null,"label":null,"bfoId":null,"name":null,"position":null,"names":null,"selected":null,"createdBy":null,"createdOn":null,"updatedBy":null,"updatedOn":null,"usedBy":null,"bfoValidationState":null,"typeName":null,"ignored":null,"preferred":null,"logoUrl":null},{"id":2324,"code":null,"label":null,"bfoId":null,"name":null,"position":null,"names":null,"selected":null,"createdBy":null,"createdOn":null,"updatedBy":null,"updatedOn":null,"usedBy":null,"bfoValidationState":null,"typeName":null,"ignored":null,"preferred":null,"logoUrl":null},{"id":2325,"code":null,"label":null,"bfoId":null,"name":null,"position":null,"names":null,"selected":null,"createdBy":null,"createdOn":null,"updatedBy":null,"updatedOn":null,"usedBy":null,"bfoValidationState":null,"typeName":null,"ignored":null,"preferred":null,"logoUrl":null},{"id":2326,"code":null,"label":null,"bfoId":null,"name":null,"position":null,"names":null,"selected":null,"createdBy":null,"createdOn":null,"updatedBy":null,"updatedOn":null,"usedBy":null,"bfoValidationState":null,"typeName":null,"ignored":null,"preferred":null,"logoUrl":null},{"id":2327,"code":null,"label":null,"bfoId":null,"name":null,"position":null,"names":null,"selected":null,"createdBy":null,"createdOn":null,"updatedBy":null,"updatedOn":null,"usedBy":null,"bfoValidationState":null,"typeName":null,"ignored":null,"preferred":null,"logoUrl":null},{"id":2328,"code":null,"label":null,"bfoId":null,"name":null,"position":null,"names":null,"selected":null,"createdBy":null,"createdOn":null,"updatedBy":null,"updatedOn":null,"usedBy":null,"bfoValidationState":null,"typeName":null,"ignored":null,"preferred":null,"logoUrl":null},{"id":2329,"code":null,"label":null,"bfoId":null,"name":null,"position":null,"names":null,"selected":null,"createdBy":null,"createdOn":null,"updatedBy":null,"updatedOn":null,"usedBy":null,"bfoValidationState":null,"typeName":null,"ignored":null,"preferred":null,"logoUrl":null},{"id":2331,"code":null,"label":null,"bfoId":null,"name":null,"position":null,"names":null,"selected":null,"createdBy":null,"createdOn":null,"updatedBy":null,"updatedOn":null,"usedBy":null,"bfoValidationState":null,"typeName":null,"ignored":null,"preferred":null,"logoUrl":null},{"id":2332,"code":null,"label":null,"bfoId":null,"name":null,"position":null,"names":null,"selected":null,"createdBy":null,"createdOn":null,"updatedBy":null,"updatedOn":null,"usedBy":null,"bfoValidationState":null,"typeName":null,"ignored":null,"preferred":null,"logoUrl":null},{"id":2333,"code":null,"label":null,"bfoId":null,"name":null,"position":null,"names":null,"selected":null,"createdBy":null,"createdOn":null,"updatedBy":null,"updatedOn":null,"usedBy":null,"bfoValidationState":null,"typeName":null,"ignored":null,"preferred":null,"logoUrl":null},{"id":2334,"code":null,"label":null,"bfoId":null,"name":null,"position":null,"names":null,"selected":null,"createdBy":null,"createdOn":null,"updatedBy":null,"updatedOn":null,"usedBy":null,"bfoValidationState":null,"typeName":null,"ignored":null,"preferred":null,"logoUrl":null},{"id":2335,"code":null,"label":null,"bfoId":null,"name":null,"position":null,"names":null,"selected":null,"createdBy":null,"createdOn":null,"updatedBy":null,"updatedOn":null,"usedBy":null,"bfoValidationState":null,"typeName":null,"ignored":null,"preferred":null,"logoUrl":null},{"id":2336,"code":null,"label":null,"bfoId":null,"name":null,"position":null,"names":null,"selected":null,"createdBy":null,"createdOn":null,"updatedBy":null,"updatedOn":null,"usedBy":null,"bfoValidationState":null,"typeName":null,"ignored":null,"preferred":null,"logoUrl":null},{"id":2337,"code":null,"label":null,"bfoId":null,"name":null,"position":null,"names":null,"selected":null,"createdBy":null,"createdOn":null,"updatedBy":null,"updatedOn":null,"usedBy":null,"bfoValidationState":null,"typeName":null,"ignored":null,"preferred":null,"logoUrl":null},{"id":2338,"code":null,"label":null,"bfoId":null,"name":null,"position":null,"names":null,"selected":null,"createdBy":null,"createdOn":null,"updatedBy":null,"updatedOn":null,"usedBy":null,"bfoValidationState":null,"typeName":null,"ignored":null,"preferred":null,"logoUrl":null},{"id":2339,"code":null,"label":null,"bfoId":null,"name":null,"position":null,"names":null,"selected":null,"createdBy":null,"createdOn":null,"updatedBy":null,"updatedOn":null,"usedBy":null,"bfoValidationState":null,"typeName":null,"ignored":null,"preferred":null,"logoUrl":null},{"id":2340,"code":null,"label":null,"bfoId":null,"name":null,"position":null,"names":null,"selected":null,"createdBy":null,"createdOn":null,"updatedBy":null,"updatedOn":null,"usedBy":null,"bfoValidationState":null,"typeName":null,"ignored":null,"preferred":null,"logoUrl":null},{"id":2342,"code":null,"label":null,"bfoId":null,"name":null,"position":null,"names":null,"selected":null,"createdBy":null,"createdOn":null,"updatedBy":null,"updatedOn":null,"usedBy":null,"bfoValidationState":null,"typeName":null,"ignored":null,"preferred":null,"logoUrl":null},{"id":2344,"code":null,"label":null,"bfoId":null,"name":null,"position":null,"names":null,"selected":null,"createdBy":null,"createdOn":null,"updatedBy":null,"updatedOn":null,"usedBy":null,"bfoValidationState":null,"typeName":null,"ignored":null,"preferred":null,"logoUrl":null},{"id":2346,"code":null,"label":null,"bfoId":null,"name":null,"position":null,"names":null,"selected":null,"createdBy":null,"createdOn":null,"updatedBy":null,"updatedOn":null,"usedBy":null,"bfoValidationState":null,"typeName":null,"ignored":null,"preferred":null,"logoUrl":null},{"id":2347,"code":null,"label":null,"bfoId":null,"name":null,"position":null,"names":null,"selected":null,"createdBy":null,"createdOn":null,"updatedBy":null,"updatedOn":null,"usedBy":null,"bfoValidationState":null,"typeName":null,"ignored":null,"preferred":null,"logoUrl":null},{"id":2349,"code":null,"label":null,"bfoId":null,"name":null,"position":null,"names":null,"selected":null,"createdBy":null,"createdOn":null,"updatedBy":null,"updatedOn":null,"usedBy":null,"bfoValidationState":null,"typeName":null,"ignored":null,"preferred":null,"logoUrl":null},{"id":2351,"code":null,"label":null,"bfoId":null,"name":null,"position":null,"names":null,"selected":null,"createdBy":null,"createdOn":null,"updatedBy":null,"updatedOn":null,"usedBy":null,"bfoValidationState":null,"typeName":null,"ignored":null,"preferred":null,"logoUrl":null},{"id":2352,"code":null,"label":null,"bfoId":null,"name":null,"position":null,"names":null,"selected":null,"createdBy":null,"createdOn":null,"updatedBy":null,"updatedOn":null,"usedBy":null,"bfoValidationState":null,"typeName":null,"ignored":null,"preferred":null,"logoUrl":null},{"id":2354,"code":null,"label":null,"bfoId":null,"name":null,"position":null,"names":null,"selected":null,"createdBy":null,"createdOn":null,"updatedBy":null,"updatedOn":null,"usedBy":null,"bfoValidationState":null,"typeName":null,"ignored":null,"preferred":null,"logoUrl":null},{"id":2356,"code":null,"label":null,"bfoId":null,"name":null,"position":null,"names":null,"selected":null,"createdBy":null,"createdOn":null,"updatedBy":null,"updatedOn":null,"usedBy":null,"bfoValidationState":null,"typeName":null,"ignored":null,"preferred":null,"logoUrl":null},{"id":2357,"code":null,"label":null,"bfoId":null,"name":null,"position":null,"names":null,"selected":null,"createdBy":null,"createdOn":null,"updatedBy":null,"updatedOn":null,"usedBy":null,"bfoValidationState":null,"typeName":null,"ignored":null,"preferred":null,"logoUrl":null},{"id":2358,"code":null,"label":null,"bfoId":null,"name":null,"position":null,"names":null,"selected":null,"createdBy":null,"createdOn":null,"updatedBy":null,"updatedOn":null,"usedBy":null,"bfoValidationState":null,"typeName":null,"ignored":null,"preferred":null,"logoUrl":null},{"id":2359,"code":null,"label":null,"bfoId":null,"name":null,"position":null,"names":null,"selected":null,"createdBy":null,"createdOn":null,"updatedBy":null,"updatedOn":null,"usedBy":null,"bfoValidationState":null,"typeName":null,"ignored":null,"preferred":null,"logoUrl":null},{"id":2360,"code":null,"label":null,"bfoId":null,"name":null,"position":null,"names":null,"selected":null,"createdBy":null,"createdOn":null,"updatedBy":null,"updatedOn":null,"usedBy":null,"bfoValidationState":null,"typeName":null,"ignored":null,"preferred":null,"logoUrl":null},{"id":2361,"code":null,"label":null,"bfoId":null,"name":null,"position":null,"names":null,"selected":null,"createdBy":null,"createdOn":null,"updatedBy":null,"updatedOn":null,"usedBy":null,"bfoValidationState":null,"typeName":null,"ignored":null,"preferred":null,"logoUrl":null},{"id":2367,"code":null,"label":null,"bfoId":null,"name":null,"position":null,"names":null,"selected":null,"createdBy":null,"createdOn":null,"updatedBy":null,"updatedOn":null,"usedBy":null,"bfoValidationState":null,"typeName":null,"ignored":null,"preferred":null,"logoUrl":null},{"id":2369,"code":null,"label":null,"bfoId":null,"name":null,"position":null,"names":null,"selected":null,"createdBy":null,"createdOn":null,"updatedBy":null,"updatedOn":null,"usedBy":null,"bfoValidationState":null,"typeName":null,"ignored":null,"preferred":null,"logoUrl":null}],"programGroup":null,"program":[],"programLevel":[],"product":[{"id":5,"code":null,"label":null,"bfoId":null,"name":null,"position":null,"names":null,"selected":null,"createdBy":null,"createdOn":null,"updatedBy":null,"updatedOn":null,"usedBy":null,"bfoValidationState":null,"typeName":null,"ignored":null,"preferred":null,"logoUrl":null},{"id":6,"code":null,"label":null,"bfoId":null,"name":null,"position":null,"names":null,"selected":null,"createdBy":null,"createdOn":null,"updatedBy":null,"updatedOn":null,"usedBy":null,"bfoValidationState":null,"typeName":null,"ignored":null,"preferred":null,"logoUrl":null},{"id":7,"code":null,"label":null,"bfoId":null,"name":null,"position":null,"names":null,"selected":null,"createdBy":null,"createdOn":null,"updatedBy":null,"updatedOn":null,"usedBy":null,"bfoValidationState":null,"typeName":null,"ignored":null,"preferred":null,"logoUrl":null},{"id":8,"code":null,"label":null,"bfoId":null,"name":null,"position":null,"names":null,"selected":null,"createdBy":null,"createdOn":null,"updatedBy":null,"updatedOn":null,"usedBy":null,"bfoValidationState":null,"typeName":null,"ignored":null,"preferred":null,"logoUrl":null},{"id":1,"code":null,"label":null,"bfoId":null,"name":null,"position":null,"names":null,"selected":null,"createdBy":null,"createdOn":null,"updatedBy":null,"updatedOn":null,"usedBy":null,"bfoValidationState":null,"typeName":null,"ignored":null,"preferred":null,"logoUrl":null},{"id":2,"code":null,"label":null,"bfoId":null,"name":null,"position":null,"names":null,"selected":null,"createdBy":null,"createdOn":null,"updatedBy":null,"updatedOn":null,"usedBy":null,"bfoValidationState":null,"typeName":null,"ignored":null,"preferred":null,"logoUrl":null},{"id":3,"code":null,"label":null,"bfoId":null,"name":null,"position":null,"names":null,"selected":null,"createdBy":null,"createdOn":null,"updatedBy":null,"updatedOn":null,"usedBy":null,"bfoValidationState":null,"typeName":null,"ignored":null,"preferred":null,"logoUrl":null},{"id":4,"code":null,"label":null,"bfoId":null,"name":null,"position":null,"names":null,"selected":null,"createdBy":null,"createdOn":null,"updatedBy":null,"updatedOn":null,"usedBy":null,"bfoValidationState":null,"typeName":null,"ignored":null,"preferred":null,"logoUrl":null}],"competence":[],"countriesIds":[135]}}