{"id":372132,"companyName":"CNW Electrical Pooraka","address1":"43 Research Rd","address2":null,"zipCode":"5095","city":"Pooraka","administrativeRegion":"South Australia","country":"Australia","countryId":109,"administrativeRegionId":539,"webSite":"http://www.cnw.com.au","webSite2":null,"emailExists":false,"phoneExists":true,"latitude":-34.82,"longitude":138.63,"accountBfoId":"001A000000nfDbmIAE","webShop":null,"active":true,"type":null,"isFromBfo":true,"eshop":false,"federatedId":"6372c85d-b70e-4f23-860b-41fbc1934d6c","partnerDetails":{"firstName":null,"lastName":null,"partnerContact":{"email":null,"phone":"08 8262 7755"},"about":null,"logoBase64":null,"photoUrl":null,"addressTemplate1":"${ct}","addressTemplate2":"","detailsAddressTemplate1":"${ad}${ca}","detailsAddressTemplate2":"${ct}${bfoSt}${cp}${con}","detailsAddressTemplate3":"","descriptions":[]},"areaOfFocus":[{"id":70,"code":"WD2","label":"Electrical&IndustrialAutomationDistributor","bfoId":null,"name":"Elektriskās rūpniecības automatizācijas izplatītājs ","position":null,"names":null,"selected":null,"createdBy":null,"createdOn":null,"updatedBy":null,"updatedOn":null,"usedBy":null,"bfoValidationState":null,"typeName":null,"ignored":false,"preferred":null,"logoUrl":null},{"id":74,"code":"WD6","label":"GeneralB2BDistributor(non-IT/non-Electrical)","bfoId":null,"name":"Ģenerālais B2B izplatītājs (ne-IT / ne elektrisks) ","position":null,"names":null,"selected":null,"createdBy":null,"createdOn":null,"updatedBy":null,"updatedOn":null,"usedBy":null,"bfoValidationState":null,"typeName":null,"ignored":false,"preferred":null,"logoUrl":null}],"businessType":[{"id":12,"code":"WD","label":"B2B Distribution","bfoId":null,"name":"Izplatītāji","position":null,"names":null,"selected":null,"createdBy":null,"createdOn":null,"updatedBy":null,"updatedOn":null,"usedBy":null,"bfoValidationState":null,"typeName":null,"ignored":false,"preferred":null,"logoUrl":null}],"domainOfExpertise":[],"marketServe":[{"id":6,"code":"EN1","label":"Power & Grid","bfoId":null,"name":"Power & Grid","position":null,"names":null,"selected":null,"createdBy":null,"createdOn":null,"updatedBy":null,"updatedOn":null,"usedBy":null,"bfoValidationState":null,"typeName":null,"ignored":null,"preferred":false,"logoUrl":null},{"id":7,"code":"EN2","label":"Oil, Gas & Petrochemicals ","bfoId":null,"name":"Oil, Gas & Petrochemicals ","position":null,"names":null,"selected":null,"createdBy":null,"createdOn":null,"updatedBy":null,"updatedOn":null,"usedBy":null,"bfoValidationState":null,"typeName":null,"ignored":null,"preferred":false,"logoUrl":null},{"id":9,"code":"ID1","label":"Machinery ","bfoId":null,"name":"Machinery ","position":null,"names":null,"selected":null,"createdBy":null,"createdOn":null,"updatedBy":null,"updatedOn":null,"usedBy":null,"bfoValidationState":null,"typeName":null,"ignored":null,"preferred":false,"logoUrl":null},{"id":10,"code":"ID2","label":"Water ","bfoId":null,"name":"Water ","position":null,"names":null,"selected":null,"createdBy":null,"createdOn":null,"updatedBy":null,"updatedOn":null,"usedBy":null,"bfoValidationState":null,"typeName":null,"ignored":null,"preferred":false,"logoUrl":null},{"id":11,"code":"ID3","label":"MMM ","bfoId":null,"name":"MMM ","position":null,"names":null,"selected":null,"createdBy":null,"createdOn":null,"updatedBy":null,"updatedOn":null,"usedBy":null,"bfoValidationState":null,"typeName":null,"ignored":null,"preferred":false,"logoUrl":null},{"id":12,"code":"ID4","label":"Food & Beverage ","bfoId":null,"name":"Food & Beverage ","position":null,"names":null,"selected":null,"createdBy":null,"createdOn":null,"updatedBy":null,"updatedOn":null,"usedBy":null,"bfoValidationState":null,"typeName":null,"ignored":null,"preferred":false,"logoUrl":null},{"id":1,"code":"BD1","label":"Wholesale & Retail Trade ","bfoId":null,"name":"Wholesale & Retail Trade ","position":null,"names":null,"selected":null,"createdBy":null,"createdOn":null,"updatedBy":null,"updatedOn":null,"usedBy":null,"bfoValidationState":null,"typeName":null,"ignored":null,"preferred":false,"logoUrl":null},{"id":18,"code":"PW1","label":"Residential ","bfoId":null,"name":"Residential ","position":null,"names":null,"selected":null,"createdBy":null,"createdOn":null,"updatedBy":null,"updatedOn":null,"usedBy":null,"bfoValidationState":null,"typeName":null,"ignored":null,"preferred":false,"logoUrl":null},{"id":3,"code":"BD4","label":"Healthcare ","bfoId":null,"name":"Healthcare ","position":null,"names":null,"selected":null,"createdBy":null,"createdOn":null,"updatedBy":null,"updatedOn":null,"usedBy":null,"bfoValidationState":null,"typeName":null,"ignored":null,"preferred":false,"logoUrl":null},{"id":4,"code":"BD9","label":"Education & Research ","bfoId":null,"name":"Education & Research ","position":null,"names":null,"selected":null,"createdBy":null,"createdOn":null,"updatedBy":null,"updatedOn":null,"usedBy":null,"bfoValidationState":null,"typeName":null,"ignored":null,"preferred":false,"logoUrl":null}],"preferredMarketServe":[],"specialization":[],"certification":[{"id":559,"code":"#AU-WD","label":"Campaign Participating Wholesaler","bfoId":null,"name":"Campaign Participating Wholesaler","position":null,"names":null,"selected":null,"createdBy":null,"createdOn":null,"updatedBy":null,"updatedOn":null,"usedBy":null,"bfoValidationState":null,"typeName":null,"ignored":false,"preferred":null,"logoUrl":null}],"associatedBrand":[],"competence":[],"openingHoursType":"NOT_SET","openingHours":[],"programGroups":[],"programLevels":[],"programs":[]}