[{"accountBfoId":"001A000000eCgErIAK","id":319141,"active":null,"country":"Indonesia","companyName":"PT Kawi Agung Kencana","address1":"Jl. Lobak no. 11, Darat","address2":"Medan Baru","zipCode":"20153","city":"Medan","phone":null,"email":null,"webSite":"http://www.kawiagungkencana.com/","webSite2":null,"createdBy":null,"createdOn":null,"updatedBy":null,"updatedOn":null,"b2cPhoto":null,"countryId":213,"latitude":3.57,"longitude":98.66,"administrativeRegion":"Sumatera Utara","stateId":1133,"webshop":null,"emailExists":true,"phoneExists":true,"openingHoursType":"NOT_SET","partnerDetails":{"firstName":"Leo Setiawan","lastName":"Tio","partnerContact":{"email":"kak@kawiagung.com","phone":"+62614158133"},"about":"LV components and MV equipments distributor for Panel Builder\nDistribute LV components, MV equipment and residential product for contractor and shops","logoBase64":null,"photoUrl":null,"addressTemplate1":null,"addressTemplate2":null,"detailsAddressTemplate1":null,"detailsAddressTemplate2":null,"detailsAddressTemplate3":null,"descriptions":[{"id":null,"languageId":null,"description":"LV components and MV equipments distributor for Panel Builder\nDistribute LV components, MV equipment and residential product for contractor and shops","isDefault":true}]},"openingHours":[],"preferredMarketServe":[],"competence":[],"areaOfFocus":[],"programLevels":[],"eshop":false,"federatedId":null}]