{"id":322920,"companyName":"J A Russell Ltd - East Tamaki","address1":"90 Greenmount Drive East Tamaki","address2":null,"zipCode":"2013","city":"Auckland","administrativeRegion":null,"country":"New Zealand","countryId":71,"administrativeRegionId":null,"webSite":"https://www.jarussell.co.nz/","webSite2":null,"emailExists":false,"phoneExists":true,"latitude":-36.928394,"longitude":174.90134,"accountBfoId":"001A000000nfEw6IAE","webShop":null,"active":true,"type":null,"isFromBfo":true,"eshop":null,"federatedId":"6372c85d-91f6-4554-9cf0-3228e3648104","partnerDetails":{"firstName":null,"lastName":null,"partnerContact":{"email":null,"phone":"09 273 7450"},"about":null,"logoBase64":null,"photoUrl":null,"addressTemplate1":"${ct}","addressTemplate2":"","detailsAddressTemplate1":"${ad}${ca}","detailsAddressTemplate2":"${ct}${bfoSt}${cp}${con}","detailsAddressTemplate3":"","descriptions":[]},"areaOfFocus":[{"id":70,"code":"WD2","label":"Electrical&IndustrialAutomationDistributor","bfoId":null,"name":"Elektriskās rūpniecības automatizācijas izplatītājs ","position":null,"names":null,"selected":null,"createdBy":null,"createdOn":null,"updatedBy":null,"updatedOn":null,"usedBy":null,"bfoValidationState":null,"typeName":null,"ignored":false,"preferred":null,"logoUrl":null}],"businessType":[{"id":12,"code":"WD","label":"B2B Distribution","bfoId":null,"name":"Izplatītāji","position":null,"names":null,"selected":null,"createdBy":null,"createdOn":null,"updatedBy":null,"updatedOn":null,"usedBy":null,"bfoValidationState":null,"typeName":null,"ignored":false,"preferred":null,"logoUrl":null}],"domainOfExpertise":[],"marketServe":[],"preferredMarketServe":[],"specialization":[],"certification":[],"associatedBrand":[],"competence":[],"openingHoursType":"NOT_SET","openingHours":[],"programGroups":[],"programLevels":[],"programs":[]}