{"id":356385,"companyName":"Equipos Industriales","address1":"Barrio Las Palmas, 3y4b AVE.27 calle SE  una cuadra al sur de Aguas de san pedro","address2":null,"zipCode":"10010","city":"San Pedro Sula","administrativeRegion":null,"country":"Honduras","countryId":205,"administrativeRegionId":null,"webSite":null,"webSite2":null,"emailExists":true,"phoneExists":false,"latitude":15.485129,"longitude":-88.02443,"accountBfoId":"0011200001LMppQAAT","webShop":null,"active":true,"type":null,"isFromBfo":true,"eshop":false,"federatedId":"6372c85d-98c3-4cf7-af43-189ea7da8269","partnerDetails":{"firstName":null,"lastName":null,"partnerContact":{"email":"santiago.luna@equiposindustriales.hn","phone":null},"about":null,"logoBase64":null,"photoUrl":null,"addressTemplate1":"${ct}","addressTemplate2":"","detailsAddressTemplate1":"${ad}${ca}","detailsAddressTemplate2":"${cp}${ct}${bfoSt}${con}","detailsAddressTemplate3":"","descriptions":[]},"areaOfFocus":[{"id":65,"code":"VR3","label":"IT Systems Integrator / VAR","bfoId":null,"name":"Turn-key IT Solutions Reseller","position":null,"names":null,"selected":null,"createdBy":null,"createdOn":null,"updatedBy":null,"updatedOn":null,"usedBy":null,"bfoValidationState":null,"typeName":null,"ignored":false,"preferred":null,"logoUrl":null}],"businessType":[{"id":11,"code":"VR","label":"IT Solution Provider","bfoId":null,"name":"IT (APC Partneri)","position":null,"names":null,"selected":null,"createdBy":null,"createdOn":null,"updatedBy":null,"updatedOn":null,"usedBy":null,"bfoValidationState":null,"typeName":null,"ignored":false,"preferred":null,"logoUrl":null}],"domainOfExpertise":[],"marketServe":[{"id":15,"code":"IT1","label":"IT Equipment and Professional Services ","bfoId":null,"name":"IT Equipment and Professional Services ","position":null,"names":null,"selected":null,"createdBy":null,"createdOn":null,"updatedBy":null,"updatedOn":null,"usedBy":null,"bfoValidationState":null,"typeName":null,"ignored":null,"preferred":false,"logoUrl":null}],"preferredMarketServe":[],"specialization":[],"certification":[],"associatedBrand":[],"competence":[],"openingHoursType":"NOT_SET","openingHours":[],"programGroups":[],"programLevels":[],"programs":[]}